{
    "display": {
      "icon": {
        "id": "minecraft:paper"
      },
      "title": "あかり",
      "description": "どうだ？明るくなっただろう？(松明を入手)",
      "background": "minecraft:textures/block/oak_planks.png",
      "show_toast": true,
      "announce_to_chat": true,
      "hidden": false
    },
    "parent": "mefours:fuel",
    "criteria": {
      "requirement": {
        "trigger": "minecraft:inventory_changed",
        "conditions": {
          "player": [],
          "items": [
            {
              "items": "minecraft:torch"
            }
          ]
        }
      }
    },
    "rewards": {
      "function": "mefours:givetorch"
    },
    "sends_telemetry_event": true
  }
  